hanzo_runtime/__init__.py
hanzo_runtime/_async/__init__.py
hanzo_runtime/_async/computer_use.py
hanzo_runtime/_async/filesystem.py
hanzo_runtime/_async/git.py
hanzo_runtime/_async/hanzo_runtime.py
hanzo_runtime/_async/lsp_server.py
hanzo_runtime/_async/object_storage.py
hanzo_runtime/_async/process.py
hanzo_runtime/_async/sandbox.py
hanzo_runtime/_async/snapshot.py
hanzo_runtime/_async/volume.py
hanzo_runtime/_sync/__init__.py
hanzo_runtime/_sync/computer_use.py
hanzo_runtime/_sync/filesystem.py
hanzo_runtime/_sync/git.py
hanzo_runtime/_sync/hanzo_runtime.py
hanzo_runtime/_sync/lsp_server.py
hanzo_runtime/_sync/object_storage.py
hanzo_runtime/_sync/process.py
hanzo_runtime/_sync/sandbox.py
hanzo_runtime/_sync/snapshot.py
hanzo_runtime/_sync/volume.py
hanzo_runtime/_utils/__init__.py
hanzo_runtime/_utils/chart_data_extractor_wrapper.py
hanzo_runtime/_utils/deprecation.py
hanzo_runtime/_utils/docs_ignore.py
hanzo_runtime/_utils/enum.py
hanzo_runtime/_utils/errors.py
hanzo_runtime/_utils/path.py
hanzo_runtime/_utils/stream.py
hanzo_runtime/_utils/timeout.py
hanzo_runtime/code_toolbox/__init__.py
hanzo_runtime/code_toolbox/sandbox_python_code_toolbox.py
hanzo_runtime/code_toolbox/sandbox_ts_code_toolbox.py
hanzo_runtime/common/__init__.py
hanzo_runtime/common/charts.py
hanzo_runtime/common/computer_use.py
hanzo_runtime/common/errors.py
hanzo_runtime/common/filesystem.py
hanzo_runtime/common/git.py
hanzo_runtime/common/hanzo_runtime.py
hanzo_runtime/common/image.py
hanzo_runtime/common/lsp_server.py
hanzo_runtime/common/process.py
hanzo_runtime/common/protocols.py
hanzo_runtime/common/sandbox.py
hanzo_runtime/common/snapshot.py
hanzo_runtime/common/volume.py
hanzo_runtime-0.7.0.dist-info/LICENSE
hanzo_runtime-0.7.0.dist-info/METADATA
hanzo_runtime-0.7.0.dist-info/WHEEL
hanzo_runtime-0.7.0.dist-info/RECORD
