Metadata-Version: 2.3
Name: hanzo-runtime
Version: 0.7.0
Summary: Python SDK for Hanzo Runtime
License: Apache-2.0
Keywords: hanzo,runtime,sdk,ai,code-execution
Author: Hanzo Industries Inc
Author-email: support@hanzo.ai
Requires-Python: >=3.8,<4.0
Classifier: Development Status :: 3 - Alpha
Classifier: Intended Audience :: Developers
Classifier: Programming Language :: Python :: 3
Classifier: Programming Language :: Python :: 3.8
Classifier: Programming Language :: Python :: 3.9
Classifier: Programming Language :: Python :: 3.10
Requires-Dist: Deprecated (>=1.2.18,<2.0.0)
Requires-Dist: aiofiles (>=24.1.0,<24.2.0)
Requires-Dist: environs (>=10.0.0,<15.0.0)
Requires-Dist: httpx (>=0.28.0,<0.29.0)
Requires-Dist: obstore (>=0.7.0,<0.8.0)
Requires-Dist: pydantic (>=2.4.2,<3.0.0)
Requires-Dist: toml (>=0.10.0,<0.11.0)
